mlproj_manager/__init__.py
mlproj_manager/definitions.py
mlproj_manager/main.py
mlproj_manager/experiments/__init__.py
mlproj_manager/experiments/abstract_experiment.py
mlproj_manager/experiments/experiment_runner.py
mlproj_manager/experiments/register_experiment.py
mlproj_manager/file_management/__init__.py
mlproj_manager/file_management/concatenate_experiment_results.py
mlproj_manager/file_management/experiment_management.py
mlproj_manager/file_management/file_and_directory_management.py
mlproj_manager/function_approximators/__init__.py
mlproj_manager/function_approximators/neural_networks/__init__.py
mlproj_manager/function_approximators/neural_networks/convolutional_network.py
mlproj_manager/function_approximators/neural_networks/general_deep_network.py
mlproj_manager/plots_and_summaries/__init__.py
mlproj_manager/plots_and_summaries/plot_results.py
mlproj_manager/plots_and_summaries/plotting_functions.py
mlproj_manager/plots_and_summaries/summaries.py
mlproj_manager/problems/__init__.py
mlproj_manager/problems/reinforcement_learning/__init__.py
mlproj_manager/problems/reinforcement_learning/abstract_rl_environment.py
mlproj_manager/problems/reinforcement_learning/mountain_car.py
mlproj_manager/problems/supervised_learning/__init__.py
mlproj_manager/problems/supervised_learning/abstract_dataset.py
mlproj_manager/problems/supervised_learning/cifar/cifar_data_loader.py
mlproj_manager/problems/supervised_learning/mnist/mnist_data_loader.py
mlproj_manager/problems/supervised_learning/target_generating_network/taget_generating_network.py
mlproj_manager/problems/supervised_learning/tiny_imagenet/tiny_imagenet_dataloader.py
mlproj_manager/util/__init__.py
mlproj_manager/util/experiments_util.py
mlproj_manager/util/data_preprocessing_and_transformations/__init__.py
mlproj_manager/util/data_preprocessing_and_transformations/image_transformations.py
mlproj_manager/util/data_preprocessing_and_transformations/normalization_and_preprocessing.py
mlproj_manager-0.0.31.dist-info/METADATA
mlproj_manager-0.0.31.dist-info/WHEEL
mlproj_manager-0.0.31.dist-info/top_level.txt
mlproj_manager-0.0.31.dist-info/RECORD
