Metadata-Version: 2.4
Name: mlproj_manager
Version: 0.0.31
Summary: A package with utilities for managing and running machine learning projects
Home-page: https://github.com/JFernando4/Research_Project_Manager
Author: J. Fernando Hernandez-Garcia
Author-email: jfhernan@ualberta.ca
License: MIT
Keywords: ml,rl
Classifier: Programming Language :: Python :: 3
Classifier: License :: OSI Approved :: MIT License
Classifier: Operating System :: OS Independent
Requires-Python: >=3.6
Requires-Dist: torch>=1.10
Requires-Dist: torchvision>=0.11
Requires-Dist: numpy>=1.17
Requires-Dist: matplotlib>=3.1
Requires-Dist: scipy>=1.3
Requires-Dist: datasets>=2.18.0
Requires-Dist: tqdm>=4.60.0
